{"id":"81ccfe3e-3540-49e3-88ae-4fde173b8c87","revision":0,"last_node_id":110,"last_link_id":198,"nodes":[{"id":66,"type":"EmptyLatentHunyuan3Dv2","pos":[-10,-570],"size":[260.2345886230469,82],"flags":{},"order":0,"mode":0,"inputs":[{"localized_name":"resolution","name":"resolution","type":"INT","widget":{"name":"resolution"},"link":null},{"localized_name":"batch_size","name":"batch_size","type":"INT","widget":{"name":"batch_size"},"link":null}],"outputs":[{"label":"LATENT","localized_name":"LATENT","name":"LATENT","type":"LATENT","links":[143]}],"properties":{"cnr_id":"comfy-core","ver":"0.3.43","Node name for S&R":"EmptyLatentHunyuan3Dv2"},"widgets_values":[3072,1]},{"id":51,"type":"CLIPVisionEncode","pos":[-10,-690],"size":[260,80],"flags":{},"order":5,"mode":0,"inputs":[{"label":"clip_vision","localized_name":"clip_vision","name":"clip_vision","type":"CLIP_VISION","link":111},{"label":"image","localized_name":"image","name":"image","type":"IMAGE","link":145},{"localized_name":"crop","name":"crop","type":"COMBO","widget":{"name":"crop"},"link":null}],"outputs":[{"label":"CLIP_VISION_OUTPUT","localized_name":"CLIP_VISION_OUTPUT","name":"CLIP_VISION_OUTPUT","type":"CLIP_VISION_OUTPUT","slot_index":0,"links":[164]}],"properties":{"cnr_id":"comfy-core","ver":"0.3.43","Node name for S&R":"CLIPVisionEncode"},"widgets_values":["none"]},{"id":3,"type":"KSampler","pos":[320,-700],"size":[315,262],"flags":{},"order":7,"mode":0,"inputs":[{"label":"model","localized_name":"model","name":"model","type":"MODEL","link":156},{"label":"positive","localized_name":"positive","name":"positive","type":"CONDITIONING","link":165},{"label":"negative","localized_name":"negative","name":"negative","type":"CONDITIONING","link":166},{"label":"latent_image","localized_name":"latent_image","name":"latent_image","type":"LATENT","link":143},{"localized_name":"seed","name":"seed","type":"INT","widget":{"name":"seed"},"link":182},{"localized_name":"steps","name":"steps","type":"INT","widget":{"name":"steps"},"link":null},{"localized_name":"cfg","name":"cfg","type":"FLOAT","widget":{"name":"cfg"},"link":null},{"localized_name":"sampler_name","name":"sampler_name","type":"COMBO","widget":{"name":"sampler_name"},"link":null},{"localized_name":"scheduler","name":"scheduler","type":"COMBO","widget":{"name":"scheduler"},"link":null},{"localized_name":"denoise","name":"denoise","type":"FLOAT","widget":{"name":"denoise"},"link":null}],"outputs":[{"label":"LATENT","localized_name":"LATENT","name":"LATENT","type":"LATENT","slot_index":0,"links":[130]}],"properties":{"cnr_id":"comfy-core","ver":"0.3.43","Node name for S&R":"KSampler"},"widgets_values":[131547567248190,"fixed",20,5,"euler","normal",1]},{"id":61,"type":"VAEDecodeHunyuan3D","pos":[660,-690],"size":[315,102],"flags":{},"order":8,"mode":0,"inputs":[{"label":"samples","localized_name":"samples","name":"samples","type":"LATENT","link":130},{"label":"vae","localized_name":"vae","name":"vae","type":"VAE","link":158},{"localized_name":"num_chunks","name":"num_chunks","type":"INT","widget":{"name":"num_chunks"},"link":null},{"localized_name":"octree_resolution","name":"octree_resolution","type":"INT","widget":{"name":"octree_resolution"},"link":null}],"outputs":[{"label":"VOXEL","localized_name":"VOXEL","name":"VOXEL","type":"VOXEL","slot_index":0,"links":[167]}],"properties":{"cnr_id":"comfy-core","ver":"0.3.43","Node name for S&R":"VAEDecodeHunyuan3D"},"widgets_values":[8000,256]},{"id":70,"type":"ModelSamplingAuraFlow","pos":[-10,-790],"size":[260,60],"flags":{},"order":4,"mode":0,"inputs":[{"label":"model","localized_name":"model","name":"model","type":"MODEL","link":155},{"localized_name":"shift","name":"shift","type":"FLOAT","widget":{"name":"shift"},"link":null}],"outputs":[{"label":"MODEL","localized_name":"MODEL","name":"MODEL","type":"MODEL","slot_index":0,"links":[156]}],"properties":{"cnr_id":"comfy-core","ver":"0.3.43","Node name for S&R":"ModelSamplingAuraFlow"},"widgets_values":[1.0000000000000002]},{"id":81,"type":"VoxelToMesh","pos":[670,-500],"size":[270,82],"flags":{},"order":9,"mode":0,"inputs":[{"localized_name":"voxel","name":"voxel","type":"VOXEL","link":167},{"localized_name":"algorithm","name":"algorithm","type":"COMBO","widget":{"name":"algorithm"},"link":null},{"localized_name":"threshold","name":"threshold","type":"FLOAT","widget":{"name":"threshold"},"link":null}],"outputs":[{"localized_name":"MESH","name":"MESH","type":"MESH","links":[168]}],"properties":{"cnr_id":"comfy-core","ver":"0.3.43","Node name for S&R":"VoxelToMesh"},"widgets_values":["surface net",0.6]},{"id":96,"type":"PrimitiveInt","pos":[-310,-80],"size":[270,82],"flags":{},"order":1,"mode":0,"inputs":[{"localized_name":"value","name":"value","type":"INT","widget":{"name":"value"},"link":null}],"outputs":[{"localized_name":"INT","name":"INT","type":"INT","links":[182]}],"properties":{"cnr_id":"comfy-core","ver":"0.3.57","Node name for S&R":"PrimitiveInt"},"widgets_values":[-929199355479881,"randomize"]},{"id":56,"type":"LoadImage","pos":[-400,-490],"size":[370,340],"flags":{},"order":2,"mode":0,"inputs":[{"localized_name":"image","name":"image","type":"COMBO","widget":{"name":"image"},"link":null},{"localized_name":"choose file to upload","name":"upload","type":"IMAGEUPLOAD","widget":{"name":"upload"},"link":null}],"outputs":[{"label":"IMAGE","localized_name":"IMAGE","name":"IMAGE","type":"IMAGE","slot_index":0,"links":[145]},{"label":"MASK","localized_name":"MASK","name":"MASK","type":"MASK","slot_index":1,"links":[]}],"properties":{"cnr_id":"comfy-core","ver":"0.3.43","Node name for S&R":"LoadImage"},"widgets_values":["ComfyUI_00011_ (1).png","image"]},{"id":54,"type":"ImageOnlyCheckpointLoader","pos":[-390,-670],"size":[369.6000061035156,98],"flags":{},"order":3,"mode":0,"inputs":[{"localized_name":"ckpt_name","name":"ckpt_name","type":"COMBO","widget":{"name":"ckpt_name"},"link":null}],"outputs":[{"label":"MODEL","localized_name":"MODEL","name":"MODEL","type":"MODEL","slot_index":0,"links":[155]},{"label":"CLIP_VISION","localized_name":"CLIP_VISION","name":"CLIP_VISION","type":"CLIP_VISION","slot_index":1,"links":[111]},{"label":"VAE","localized_name":"VAE","name":"VAE","type":"VAE","slot_index":2,"links":[158]}],"properties":{"cnr_id":"comfy-core","ver":"0.3.43","Node name for S&R":"ImageOnlyCheckpointLoader","models":[{"name":"hunyuan3d-dit-v2_fp16.safetensors","url":"https://huggingface.co/Comfy-Org/hunyuan3D_2.0_repackaged/resolve/main/split_files/hunyuan3d-dit-v2_fp16.safetensors","directory":"checkpoints"}]},"widgets_values":["hunyuan3d-dit-v2_fp16.safetensors"],"color":"#322","bgcolor":"#533"},{"id":80,"type":"Hunyuan3Dv2Conditioning","pos":[340,-820],"size":[310,50],"flags":{},"order":6,"mode":0,"inputs":[{"localized_name":"clip_vision_output","name":"clip_vision_output","type":"CLIP_VISION_OUTPUT","link":164}],"outputs":[{"localized_name":"positive","name":"positive","type":"CONDITIONING","slot_index":0,"links":[165]},{"localized_name":"negative","name":"negative","type":"CONDITIONING","slot_index":1,"links":[166]}],"properties":{"cnr_id":"comfy-core","ver":"0.3.43","Node name for S&R":"Hunyuan3Dv2Conditioning"},"widgets_values":[]},{"id":82,"type":"SaveGLB","pos":[150,-350],"size":[532.7781982421875,481.68194580078125],"flags":{},"order":10,"mode":0,"inputs":[{"label":"mesh","localized_name":"mesh","name":"mesh","type":"MESH","link":168},{"localized_name":"filename_prefix","name":"filename_prefix","type":"STRING","widget":{"name":"filename_prefix"},"link":null},{"localized_name":"image","name":"image","type":"PREVIEW_3D","widget":{"name":"image"},"link":null}],"outputs":[],"title":"Save 2.0","properties":{"cnr_id":"comfy-core","ver":"0.3.43","Node name for S&R":"SaveGLB","Camera Info":{"position":{"x":-4.8758090465716135,"y":2.0410607626040784,"z":14.626379846015302},"target":{"x":0,"y":2.0468005983395097,"z":0},"zoom":2.1584695217631853,"cameraType":"orthographic"},"Background Color":"#000000","Light Intensity":3,"FOV":63,"Camera Type":"orthographic","Background Image":"","Show Grid":true},"widgets_values":["mesh/ComfyUI",""]}],"links":[[111,54,1,51,0,"CLIP_VISION"],[130,3,0,61,0,"LATENT"],[143,66,0,3,3,"LATENT"],[145,56,0,51,1,"IMAGE"],[155,54,0,70,0,"MODEL"],[156,70,0,3,0,"MODEL"],[158,54,2,61,1,"VAE"],[164,51,0,80,0,"CLIP_VISION_OUTPUT"],[165,80,0,3,1,"CONDITIONING"],[166,80,1,3,2,"CONDITIONING"],[167,61,0,81,0,"VOXEL"],[168,81,0,82,0,"MESH"],[182,96,0,3,4,"INT"]],"groups":[],"config":{},"extra":{"ds":{"scale":0.7646251029937563,"offset":[1298.9104918055407,978.2191278779538]},"frontendVersion":"1.23.4","node_versions":{"comfy-core":"0.3.35"},"VHS_latentpreview":false,"VHS_latentpreviewrate":0,"VHS_MetadataImage":true,"VHS_KeepIntermediate":true},"version":0.4}